odoo/addons/helpdesk_ticket_open_tab/README.rst
odoo/addons/helpdesk_ticket_open_tab/__init__.py
odoo/addons/helpdesk_ticket_open_tab/__manifest__.py
odoo/addons/helpdesk_ticket_open_tab/i18n/.empty
odoo/addons/helpdesk_ticket_open_tab/i18n/helpdesk_ticket_open_tab.pot
odoo/addons/helpdesk_ticket_open_tab/i18n/it.po
odoo/addons/helpdesk_ticket_open_tab/readme/CONTRIBUTORS.md
odoo/addons/helpdesk_ticket_open_tab/readme/DESCRIPTION.md
odoo/addons/helpdesk_ticket_open_tab/readme/USAGE.md
odoo/addons/helpdesk_ticket_open_tab/static/description/icon.png
odoo/addons/helpdesk_ticket_open_tab/static/description/index.html
odoo/addons/helpdesk_ticket_open_tab/views/helpdesk_ticket_views.xml
odoo_addon_helpdesk_ticket_open_tab-18.0.1.0.0.2.dist-info/METADATA
odoo_addon_helpdesk_ticket_open_tab-18.0.1.0.0.2.dist-info/WHEEL
odoo_addon_helpdesk_ticket_open_tab-18.0.1.0.0.2.dist-info/top_level.txt
odoo_addon_helpdesk_ticket_open_tab-18.0.1.0.0.2.dist-info/RECORD
